__init__.py
engines4ai/engines.py
engines4ai/general.py
engines4ai/images.py
engines4ai/it.py
engines4ai/map.py
engines4ai/news.py
engines4ai/science.py
engines4ai/searxng.py
engines4ai/videos.py
engines4ai/wikipedia.py
engines4ai-1.0.7.dist-info/METADATA
engines4ai-1.0.7.dist-info/WHEEL
engines4ai-1.0.7.dist-info/top_level.txt
engines4ai-1.0.7.dist-info/RECORD
