Metadata-Version: 2.4
Name: engines4ai
Version: 1.0.7
Summary: A comprehensive Python wrapper for SearXNG search API, providing specialized search engines for various categories (general, images, videos, news, maps, IT, science) with structured dataclass-based results.
Author-email: Keisuke Miyamoto <miyamotokeisuke0727@gmail.com>
Requires-Python: >=3.7
Requires-Dist: certifi
Requires-Dist: charset-normalizer
Requires-Dist: idna
Requires-Dist: python-dotenv
Requires-Dist: requests
Requires-Dist: urllib3
